pybatchclassyfire/__init__.py
pybatchclassyfire/pybatchclassyfire.py
pybatchclassyfire-0.1.6.dist-info/LICENSE.md
pybatchclassyfire-0.1.6.dist-info/METADATA
pybatchclassyfire-0.1.6.dist-info/WHEEL
pybatchclassyfire-0.1.6.dist-info/top_level.txt
pybatchclassyfire-0.1.6.dist-info/RECORD
